untangle.py
untangle-1.2.0.dist-info/AUTHORS
untangle-1.2.0.dist-info/LICENSE
untangle-1.2.0.dist-info/METADATA
untangle-1.2.0.dist-info/WHEEL
untangle-1.2.0.dist-info/top_level.txt
untangle-1.2.0.dist-info/RECORD
